aws_cdk/asset_awscli_v1/_jsii/__init__.py
aws_cdk/asset_awscli_v1/_jsii/asset-awscli-v1@2.2.264.jsii.tgz
aws_cdk_asset_awscli_v1-2.2.264.dist-info/LICENSE
aws_cdk_asset_awscli_v1-2.2.264.dist-info/METADATA
aws_cdk_asset_awscli_v1-2.2.264.dist-info/NOTICE
aws_cdk_asset_awscli_v1-2.2.264.dist-info/WHEEL
aws_cdk_asset_awscli_v1-2.2.264.dist-info/top_level.txt
aws_cdk_asset_awscli_v1-2.2.264.dist-info/RECORD
