Metadata-Version: 2.1
Name: aws-cdk.asset-awscli-v1
Version: 2.2.264
Summary: A library that contains the AWS CLI for use in Lambda Layers
Home-page: https://github.com/cdklabs/awscdk-asset-awscli#readme
Author: Amazon Web Services<aws-cdk-dev@amazon.com>
License: Apache-2.0
Project-URL: Source, https://github.com/cdklabs/awscdk-asset-awscli.git
Classifier: Intended Audience :: Developers
Classifier: Operating System :: OS Independent
Classifier: Programming Language :: JavaScript
Classifier: Programming Language :: Python :: 3 :: Only
Classifier: Programming Language :: Python :: 3.9
Classifier: Programming Language :: Python :: 3.10
Classifier: Programming Language :: Python :: 3.11
Classifier: Typing :: Typed
Classifier: Development Status :: 5 - Production/Stable
Classifier: License :: OSI Approved
Requires-Python: ~=3.9
License-File: LICENSE
License-File: NOTICE
Requires-Dist: jsii <2.0.0,>=1.125.0
Requires-Dist: publication >=0.0.3
Requires-Dist: typeguard ==2.13.3
